maprouletteupload/__init__.py
maprouletteupload/api.py
maprouletteupload/cmd.py
maprouletteupload/config.py
maprouletteupload/tasks.py
maprouletteupload-0.1.0.dist-info/DESCRIPTION.rst
maprouletteupload-0.1.0.dist-info/METADATA
maprouletteupload-0.1.0.dist-info/RECORD
maprouletteupload-0.1.0.dist-info/WHEEL
maprouletteupload-0.1.0.dist-info/entry_points.txt
maprouletteupload-0.1.0.dist-info/metadata.json
maprouletteupload-0.1.0.dist-info/top_level.txt
