Metadata-Version: 2.0
Name: maprouletteupload
Version: 0.1.0
Summary: A simple Maproulette uploader
Home-page: UNKNOWN
Author: Eric Brelsford
Author-email: ebrelsford@gmail.com
License: MIT
Keywords: maps maproulette openstreetmap
Platform: UNKNOWN
Classifier: Development Status :: 3 - Alpha
Classifier: License :: OSI Approved :: MIT License
Classifier: Programming Language :: Python :: 3
Classifier: Programming Language :: Python :: 3.3
Classifier: Programming Language :: Python :: 3.4
Classifier: Programming Language :: Python :: 3.5
Requires-Dist: click
Requires-Dist: geojson
Requires-Dist: requests
